mdspec/__init__.py
mdspec/parser.py
mdspec-0.0.2.dist-info/LICENSE
mdspec-0.0.2.dist-info/WHEEL
mdspec-0.0.2.dist-info/METADATA
mdspec-0.0.2.dist-info/RECORD
