Metadata-Version: 2.1
Name: mdspec
Version: 0.0.2
Summary: Declarative plain-text specifications for objects
Author: Daniel Fairhead
Author-email: danthedeckie@gmail.com
Requires-Python: >=3.8,<4.0
Classifier: Programming Language :: Python :: 3
Classifier: Programming Language :: Python :: 3.8
Classifier: Programming Language :: Python :: 3.9
Classifier: Programming Language :: Python :: 3.10
Classifier: Programming Language :: Python :: 3.11
